odoo/addons/product_packaging_type_pallet/README.rst
odoo/addons/product_packaging_type_pallet/__init__.py
odoo/addons/product_packaging_type_pallet/__manifest__.py
odoo/addons/product_packaging_type_pallet/i18n/es.po
odoo/addons/product_packaging_type_pallet/i18n/product_packaging_type_pallet.pot
odoo/addons/product_packaging_type_pallet/models/__init__.py
odoo/addons/product_packaging_type_pallet/models/product_packaging.py
odoo/addons/product_packaging_type_pallet/readme/CONTRIBUTORS.rst
odoo/addons/product_packaging_type_pallet/readme/DESCRIPTION.rst
odoo/addons/product_packaging_type_pallet/readme/README.md
odoo/addons/product_packaging_type_pallet/static/description/icon.png
odoo/addons/product_packaging_type_pallet/static/description/index.html
odoo/addons/product_packaging_type_pallet/views/product_packaging.xml
odoo/addons/product_packaging_type_pallet/views/product_packaging_type.xml
odoo14_addon_product_packaging_type_pallet-14.0.1.0.1.dist-info/METADATA
odoo14_addon_product_packaging_type_pallet-14.0.1.0.1.dist-info/WHEEL
odoo14_addon_product_packaging_type_pallet-14.0.1.0.1.dist-info/top_level.txt
odoo14_addon_product_packaging_type_pallet-14.0.1.0.1.dist-info/RECORD
